DDLj/DDLj.py
DDLj/__init__.py
DDLJ-0.0.3.dist-info/LICENSE.txt
DDLJ-0.0.3.dist-info/METADATA
DDLJ-0.0.3.dist-info/WHEEL
DDLJ-0.0.3.dist-info/top_level.txt
DDLJ-0.0.3.dist-info/RECORD
