Metadata-Version: 2.1
Name: DDLJ
Version: 0.0.3
Summary: JSON Utils for generating DDL from JSON Schema
Home-page: https://github.com/deepstartup/jsonutils
Author: Arghadeep Chaudhury,Siddhartha Bhattacharya
Author-email: siddhbhatt@gmail.com,arghadeep.chaudhury@gmail.com
License: UNKNOWN
Platform: UNKNOWN
Classifier: Programming Language :: Python :: 3
Classifier: License :: OSI Approved :: MIT License
Classifier: Operating System :: OS Independent
Requires-Dist: pandas
Requires-Dist: flatten-json
